api_gl/__init__.py
api_gl/bank.py
api_gl/oop.py
kritika_api-0.1.dist-info/License.txt
kritika_api-0.1.dist-info/METADATA
kritika_api-0.1.dist-info/WHEEL
kritika_api-0.1.dist-info/top_level.txt
kritika_api-0.1.dist-info/RECORD
